hspylib/.version
hspylib/__classpath__.py
hspylib/__init__.py
hspylib/core/__init__.py
hspylib/core/collection_filter.py
hspylib/core/constants.py
hspylib/core/namespace.py
hspylib/core/object_mapper.py
hspylib/core/preconditions.py
hspylib/core/zoned_datetime.py
hspylib/core/config/__init__.py
hspylib/core/config/app_config.py
hspylib/core/config/parser_factory.py
hspylib/core/config/path_object.py
hspylib/core/config/properties.py
hspylib/core/config/settings.py
hspylib/core/decorator/__init__.py
hspylib/core/decorator/decorators.py
hspylib/core/enums/__init__.py
hspylib/core/enums/charset.py
hspylib/core/enums/content_type.py
hspylib/core/enums/enumeration.py
hspylib/core/enums/http_code.py
hspylib/core/enums/http_method.py
hspylib/core/exception/__init__.py
hspylib/core/exception/exceptions.py
hspylib/core/metaclass/__init__.py
hspylib/core/metaclass/classpath.py
hspylib/core/metaclass/singleton.py
hspylib/core/tools/__init__.py
hspylib/core/tools/commons.py
hspylib/core/tools/cron_utils.py
hspylib/core/tools/dict_tools.py
hspylib/core/tools/json_path.py
hspylib/core/tools/text_tools.py
hspylib/core/tools/validator.py
hspylib/modules/__init__.py
hspylib/modules/application/__init__.py
hspylib/modules/application/application.py
hspylib/modules/application/exit_hooks.py
hspylib/modules/application/exit_status.py
hspylib/modules/application/version.py
hspylib/modules/application/argparse/__init__.py
hspylib/modules/application/argparse/argument_parser.py
hspylib/modules/application/argparse/arguments_builder.py
hspylib/modules/application/argparse/chained_arguments_builder.py
hspylib/modules/application/argparse/options_builder.py
hspylib/modules/application/argparse/parser_action.py
hspylib/modules/cache/__init__.py
hspylib/modules/cache/ttl_cache.py
hspylib/modules/cache/ttl_keyring_be.py
hspylib/modules/cli/__init__.py
hspylib/modules/cli/keyboard.py
hspylib/modules/cli/vt100/__init__.py
hspylib/modules/cli/vt100/vt_100.py
hspylib/modules/cli/vt100/vt_code.py
hspylib-1.12.54.dist-info/METADATA
hspylib-1.12.54.dist-info/WHEEL
hspylib-1.12.54.dist-info/top_level.txt
hspylib-1.12.54.dist-info/RECORD
