Metadata-Version: 2.1
Name: hspylib
Version: 1.12.54
Summary: HsPyLib - Core python library
Home-page: https://github.com/yorevs/hspylib
Author: Hugo Saporetti Junior
Author-email: yorevs@hotmail.com
License: MIT
Project-URL: GitHub, https://github.com/yorevs/hspylib
Project-URL: PyPi, https://pypi.org/project/hspylib/
Keywords: python,library,solid,patterns,development,integration,application,framework
Platform: Darwin
Platform: Linux
Classifier: License :: OSI Approved :: MIT License
Classifier: Programming Language :: Python :: 3.10
Classifier: Operating System :: MacOS :: MacOS X
Classifier: Operating System :: POSIX :: Linux
Classifier: Operating System :: Unix
Classifier: Development Status :: 4 - Beta
Classifier: Natural Language :: English
Classifier: Topic :: Software Development :: Libraries :: Python Modules
Classifier: Topic :: Software Development :: Libraries :: Application Frameworks
Classifier: Intended Audience :: Developers
Requires-Python: >=3.10
Requires-Dist: get-key >=1.60.0
Requires-Dist: retry2 >=0.9.5
Requires-Dist: requests >=2.32.3
Requires-Dist: urllib3 >=1.26.20
Requires-Dist: keyring >=25.5.0
Requires-Dist: pyparsing >=3.1.2
Requires-Dist: pyperclip >=1.9.0
Requires-Dist: PyYAML >=6.0.1
Requires-Dist: toml >=0.10.2
Requires-Dist: rich >=13.8.1
